fabrique_actor/__init__.py
fabrique_actor/actors.py
fabrique_actor/dummy.py
fabrique_actor/env2configs.py
fabrique_actor/kafka_admin.py
fabrique_actor/logger.py
fabrique_actor/message.py
fabrique_actor/pipeline_actors.py
fabrique_actor/bin/__init__.py
fabrique_actor/bin/actor_boilerplate.py
fabrique_actor/bin/start_fabrique_pipeline.py
fabrique_actor/data/collector/actor.py
fabrique_actor/data/collector/template.yml
fabrique_actor/data/collector/tests/test_10_start_emulation.py
fabrique_actor/data/common/.gitignore
fabrique_actor/data/common/README.md
fabrique_actor/data/common/requirements.txt
fabrique_actor/data/common/starter.py
fabrique_actor/data/dispatcher/actor.py
fabrique_actor/data/dispatcher/template.yml
fabrique_actor/data/dispatcher/tests/test_10_start_emulation.py
fabrique_actor/data/emitter/actor.py
fabrique_actor/data/emitter/template.yml
fabrique_actor/data/emitter/tests/test_10_start_emulation.py
fabrique_actor/data/processor/actor.py
fabrique_actor/data/processor/template.yml
fabrique_actor/data/processor/tests/test_10_start_emulation.py
fabrique_actor-5.0.6.data/scripts/actor_boilerplate.py
fabrique_actor-5.0.6.data/scripts/start_fabrique_pipeline.py
fabrique_actor-5.0.6.dist-info/METADATA
fabrique_actor-5.0.6.dist-info/WHEEL
fabrique_actor-5.0.6.dist-info/top_level.txt
fabrique_actor-5.0.6.dist-info/RECORD
