Metadata-Version: 2.1
Name: fabrique-actor
Version: 5.0.6
Summary: Fabrique actor transport layer engine
Home-page: http://www.fabrique.ai
Author: Sergey Kuzmin
Author-email: sergey.kuzmin@fabrique.ai
License: MIT
Keywords: kafka
Platform: UNKNOWN
Classifier: Development Status :: 5 - Production/Stable
Classifier: License :: OSI Approved :: MIT License
Requires-Dist: confluent-kafka (>=1.2.0)
Requires-Dist: fabrique-atelier (==5.*,>=5.0.5)
Requires-Dist: python-dotenv
